CHANGELOG.txt
LICENSE
MANIFEST.in
README.md
setup.cfg
setup.py
airflow/__init__.py
airflow/alembic.ini
airflow/configuration.py
airflow/default_login.py
airflow/exceptions.py
airflow/jobs.py
airflow/logging_config.py
airflow/models.py
airflow/plugins_manager.py
airflow/settings.py
airflow/version.py
airflow/bin/airflow
airflow/api/__init__.py
airflow/api/auth/__init__.py
airflow/api/auth/backend/__init__.py
airflow/api/auth/backend/default.py
airflow/api/auth/backend/deny_all.py
airflow/api/auth/backend/kerberos_auth.py
airflow/api/auth/backend/smart_auth.py
airflow/api/client/__init__.py
airflow/api/client/api_client.py
airflow/api/client/json_client.py
airflow/api/client/local_client.py
airflow/api/common/__init__.py
airflow/api/common/experimental/__init__.py
airflow/api/common/experimental/delete_dag.py
airflow/api/common/experimental/gen_dag_file.py
airflow/api/common/experimental/get_dag_run_state.py
airflow/api/common/experimental/get_dag_runs.py
airflow/api/common/experimental/get_task.py
airflow/api/common/experimental/get_task_instance.py
airflow/api/common/experimental/mark_tasks.py
airflow/api/common/experimental/pool.py
airflow/api/common/experimental/trigger_dag.py
airflow/bin/__init__.py
airflow/bin/cli.py
airflow/config_templates/__init__.py
airflow/config_templates/airflow_local_settings.py
airflow/config_templates/default_airflow.cfg
airflow/config_templates/default_celery.py
airflow/config_templates/default_test.cfg
airflow/config_templates/default_webserver_config.py
airflow/config_templates/__pycache__/__init__.cpython-36.pyc
airflow/config_templates/__pycache__/airflow_local_settings.cpython-36.pyc
airflow/config_templates/__pycache__/default_celery.cpython-36.pyc
airflow/config_templates/__pycache__/default_webserver_config.cpython-36.pyc
airflow/contrib/__init__.py
airflow/contrib/auth/__init__.py
airflow/contrib/auth/backends/__init__.py
airflow/contrib/auth/backends/github_enterprise_auth.py
airflow/contrib/auth/backends/google_auth.py
smartpip.egg-info/PKG-INFO
smartpip.egg-info/SOURCES.txt
smartpip.egg-info/dependency_links.txt
smartpip.egg-info/not-zip-safe
smartpip.egg-info/requires.txt
smartpip.egg-info/top_level.txt