Metadata-Version: 1.2
Name: smartpip
Version: 1.11.6
Summary: Programmatically author, schedule and monitor data pipelines
Home-page: https://www.smartchart.cn/
Author: JohnYan
Author-email: 84345999@qq.com
License: Apache License 2.0
Download-URL: https://dist.apache.org/repos/dist/release/incubator/airflow/1.11.6
Platform: UNKNOWN
Classifier: Development Status :: 5 - Production/Stable
Classifier: Environment :: Console
Classifier: Environment :: Web Environment
Classifier: Intended Audience :: Developers
Classifier: Intended Audience :: System Administrators
Classifier: License :: OSI Approved :: Apache Software License
Classifier: Programming Language :: Python :: 2.7
Classifier: Programming Language :: Python :: 3.4
Classifier: Programming Language :: Python :: 3.5
Classifier: Topic :: System :: Monitoring
Requires-Python: >=2.7,!=3.0.*,!=3.1.*,!=3.2.*,!=3.3.*
